AbdoELBALFF/GG.wav
AbdoELBALFF/__init__.py
AbdoELBALFF/abdo.png
AbdoELBALFF/main.py
AbdoELBALFF-0.1.dist-info/METADATA
AbdoELBALFF-0.1.dist-info/WHEEL
AbdoELBALFF-0.1.dist-info/top_level.txt
AbdoELBALFF-0.1.dist-info/RECORD
