Metadata-Version: 2.1
Name: AbdoELBALFF
Version: 0.1
Requires-Dist: Pillow >=7.0.0
Requires-Dist: playsound ~=1.2.2
